taxdumpy/__init__.py
taxdumpy/__main__.py
taxdumpy/ansi.py
taxdumpy/basic.py
taxdumpy/cli.py
taxdumpy/database.py
taxdumpy/functions.py
taxdumpy/taxdb.py
taxdumpy/taxon.py
taxdumpy/taxsqlite.py
taxdumpy-1.1.7.dist-info/METADATA
taxdumpy-1.1.7.dist-info/WHEEL
taxdumpy-1.1.7.dist-info/entry_points.txt
taxdumpy-1.1.7.dist-info/licenses/LICENSE
taxdumpy-1.1.7.dist-info/RECORD
