Metadata-Version: 2.4
Name: taxdumpy
Version: 1.1.7
Summary: Python package for efficiently parsing NCBI's taxdump database
Project-URL: Documentation, https://github.com/omegahh/taxdumpy
Project-URL: Issues, https://github.com/omegahh/taxdumpy/issues
Project-URL: Source, https://github.com/omegahh/taxdumpy
Author-email: Omega HH <omeganju@gmail.com>
License: MIT License
License-File: LICENSE
Keywords: NCBI,metagenomics,taxonomy,tree-of-life
Classifier: Development Status :: 5 - Production/Stable
Classifier: License :: OSI Approved :: MIT License
Classifier: Operating System :: OS Independent
Classifier: Programming Language :: Python
Classifier: Programming Language :: Python :: 3.10
Classifier: Programming Language :: Python :: 3.11
Classifier: Programming Language :: Python :: 3.12
Classifier: Programming Language :: Python :: 3.13
Requires-Python: >=3.10
Requires-Dist: rapidfuzz
Requires-Dist: tqdm
Provides-Extra: dev
Requires-Dist: build; extra == 'dev'
Requires-Dist: pytest; extra == 'dev'
Requires-Dist: pytest-cov; extra == 'dev'
Requires-Dist: pytest-mock; extra == 'dev'
Requires-Dist: ruff; extra == 'dev'
